object_detection_fastai/__init__.py
object_detection_fastai/callbacks/__init__.py
object_detection_fastai/callbacks/callbacks.py
object_detection_fastai/helper/BoundingBox.py
object_detection_fastai/helper/BoundingBoxes.py
object_detection_fastai/helper/Evaluator.py
object_detection_fastai/helper/__init__.py
object_detection_fastai/helper/nms.py
object_detection_fastai/helper/nms_center_distance.py
object_detection_fastai/helper/nms_grid.py
object_detection_fastai/helper/object_detection_helper.py
object_detection_fastai/helper/utils.py
object_detection_fastai/helper/wsi_loader.py
object_detection_fastai/loss/DetrCriterion.py
object_detection_fastai/loss/RetinaNetFocalLoss.py
object_detection_fastai/loss/__init__.py
object_detection_fastai/models/Detr.py
object_detection_fastai/models/RetinaNet.py
object_detection_fastai/models/__init__.py
object_detection_fastai-0.0.10.dist-info/METADATA
object_detection_fastai-0.0.10.dist-info/WHEEL
object_detection_fastai-0.0.10.dist-info/top_level.txt
object_detection_fastai-0.0.10.dist-info/RECORD
