Metadata-Version: 2.1
Name: object-detection-fastai
Version: 0.0.10
Summary: Uses RetinaNet with FastAi
Home-page: https://github.com/ChristianMarzahl/ObjectDetection
Author: Christian Marzahl
Author-email: christian.marzahl@gamil.com
License: UNKNOWN
Platform: UNKNOWN
Classifier: Programming Language :: Python :: 3
Classifier: License :: OSI Approved :: MIT License
Classifier: Operating System :: OS Independent
Requires-Python: >=3.6
Requires-Dist: numpy
Requires-Dist: torch (>=1.5.0)
Requires-Dist: torchvision (>=0.6.0)
Requires-Dist: fastai (==1.0.61)
Requires-Dist: opencv-python (>=4.5.1.48)
Requires-Dist: openslide-python (>=1.1.1)
Requires-Dist: scikit-learn
